{"title":"Mini Serre - 3D model by Emrick.D on Thangs","type":"video.other","url":"https://thangs.com/designer/Emrick.D/3d-model/Mini%20Serre-994640","image":"https://thangs.com/_next/image?url=https%3A%2F%2Fstorage.googleapis.com%2Fproduction-thangs-public%2Fuploads%2Fattachments%2F0d5d9206-650b-4966-81ea-e2ce5434ee89%2FIMG_5563.jpg&w=1200&q=75","image_secure_url":null,"image_type":null,"image_width":null,"image_height":null,"image_alt":null,"video":null,"video_secure_url":"https://thangs.com/model/994640/embed?utm_source=embed","video_type":"text/html","video_width":"800","video_height":"600","audio":null,"audio_secure_url":null,"audio_type":null,"description":"Bienvenue dans le monde captivant de la culture des plantes avec notre mini serre à graines en acrylique, un mariage harmonieux entre la technologie moderne de ","determiner":null,"locale":null,"locale_alternate":null,"site_name":"Thangs","domain":"thangs.com"}