{"title":"Distributeur de bonbon.stl - 3D model by MathieuPion on Thangs","type":"video.other","url":"https://thangs.com/designer/MathieuPion/3d-model/Distributeur%20de%20bonbon.stl-994613","image":"https://thangs.com/_next/image?url=https%3A%2F%2Fstorage.googleapis.com%2Fproduction-thangs-public%2Fuploads%2Fattachments%2Fb8186c20-d566-4e8e-8df4-a67f131adbf6%2FDistributeur.jpg&w=1200&q=75","image_secure_url":null,"image_type":null,"image_width":null,"image_height":null,"image_alt":null,"video":null,"video_secure_url":"https://thangs.com/model/994613/embed?utm_source=embed","video_type":"text/html","video_width":"800","video_height":"600","audio":null,"audio_secure_url":null,"audio_type":null,"description":"Ce projet est un distributeur de bonbon fonctionnel réalisé dans le cadre de nos projets de deuxième année en ITEC au sein d'Unilasalle Amiens.\nCelui-ci comport","determiner":null,"locale":null,"locale_alternate":null,"site_name":"Thangs","domain":"thangs.com"}